dm/__init__.py
dm/_registry.py
dm/_xml_interrogation.py
dm/businesses.py
dm/country.py
dm/proximity.py
dm/spatial.py
dm/utils.py
modeling/__init__.py
modeling/_registry.py
modeling/_xml_interrogation.py
modeling/accessor.py
modeling/country.py
modeling/proximity.py
modeling/spatial.py
modeling/utils.py
demographic_modeling-0.3.0.dist-info/LICENSE
demographic_modeling-0.3.0.dist-info/METADATA
demographic_modeling-0.3.0.dist-info/WHEEL
demographic_modeling-0.3.0.dist-info/top_level.txt
demographic_modeling-0.3.0.dist-info/RECORD
