Metadata-Version: 2.1
Name: demographic-modeling
Version: 0.3.0
Summary: Demographic Modeling
Home-page: UNKNOWN
Author: Joel McCune
License: Apache 2.0
Platform: UNKNOWN
